cvsutils/__init__.py
cvsutils/common.py
cvsutils/dataset.py
cvsutils/evaluator.py
cvsutils/prediction_api.py
cvsutils/training_api.py
cvsutils/commands/__init__.py
cvsutils/commands/add_images.py
cvsutils/commands/create_project.py
cvsutils/commands/download_predictions.py
cvsutils/commands/download_project.py
cvsutils/commands/evaluate_project.py
cvsutils/commands/export_model.py
cvsutils/commands/get_domains.py
cvsutils/commands/list_projects.py
cvsutils/commands/predict_dataset.py
cvsutils/commands/predict_image.py
cvsutils/commands/remove_iteration.py
cvsutils/commands/show_project.py
cvsutils/commands/train_project.py
cvsutils/commands/validate_dataset_file.py
cvsutils-0.1.11.dist-info/LICENSE
cvsutils-0.1.11.dist-info/METADATA
cvsutils-0.1.11.dist-info/WHEEL
cvsutils-0.1.11.dist-info/entry_points.txt
cvsutils-0.1.11.dist-info/top_level.txt
cvsutils-0.1.11.dist-info/RECORD
