Metadata-Version: 2.1
Name: cvsutils
Version: 0.1.11
Summary: Unofficial utility scripts for Microsoft Custom Vision Service
Home-page: https://github.com/shonohs/cvsutils
License: MIT
Platform: UNKNOWN
Classifier: Intended Audience :: Developers
Classifier: License :: OSI Approved :: MIT License
Requires-Dist: Pillow
Requires-Dist: requests
Requires-Dist: tenacity
Requires-Dist: tqdm
